steov/__init__.py
steov-0.1.12.dist-info/LICENSE.txt
steov-0.1.12.dist-info/METADATA
steov-0.1.12.dist-info/WHEEL
steov-0.1.12.dist-info/top_level.txt
steov-0.1.12.dist-info/RECORD
